MANIFEST.in
README.md
setup.py
xxmind/__init__.py
xxmind/__init__.pyc
xxmind/__version__.py
xxmind/favicon.ico
xxmind/main.py
xxmind/ui2.py
xxmind/ui3.py
xxmind.egg-info/PKG-INFO
xxmind.egg-info/SOURCES.txt
xxmind.egg-info/dependency_links.txt
xxmind.egg-info/requires.txt
xxmind.egg-info/top_level.txt
xxmind.egg-info/zip-safe
xxmind/__pycache__/__init__.cpython-37.pyc
xxmind/__pycache__/__version__.cpython-37.pyc
xxmind/file/xmind-sdk-python-master/.gitignore
xxmind/file/xmind-sdk-python-master/LICENSE.md
xxmind/file/xmind-sdk-python-master/README.md
xxmind/file/xmind-sdk-python-master/example.py
xxmind/file/xmind-sdk-python-master/example2.py
xxmind/file/xmind-sdk-python-master/logo.jpeg
xxmind/file/xmind-sdk-python-master/mac.xmind
xxmind/file/xmind-sdk-python-master/setup.py
xxmind/file/xmind-sdk-python-master/test2.xmind
xxmind/file/xmind-sdk-python-master/build/lib/xmind/__init__.py
xxmind/file/xmind-sdk-python-master/build/lib/xmind/utils.py
xxmind/file/xmind-sdk-python-master/build/lib/xmind/core/__init__.py
xxmind/file/xmind-sdk-python-master/build/lib/xmind/core/const.py
xxmind/file/xmind-sdk-python-master/build/lib/xmind/core/loader.py
xxmind/file/xmind-sdk-python-master/build/lib/xmind/core/markerref.py
xxmind/file/xmind-sdk-python-master/build/lib/xmind/core/mixin.py
xxmind/file/xmind-sdk-python-master/build/lib/xmind/core/notes.py
xxmind/file/xmind-sdk-python-master/build/lib/xmind/core/position.py
xxmind/file/xmind-sdk-python-master/build/lib/xmind/core/relationship.py
xxmind/file/xmind-sdk-python-master/build/lib/xmind/core/saver.py
xxmind/file/xmind-sdk-python-master/build/lib/xmind/core/sheet.py
xxmind/file/xmind-sdk-python-master/build/lib/xmind/core/title.py
xxmind/file/xmind-sdk-python-master/build/lib/xmind/core/topic.py
xxmind/file/xmind-sdk-python-master/build/lib/xmind/core/workbook.py
xxmind/file/xmind-sdk-python-master/dist/xmind-0.1a0-py2.7.egg
xxmind/file/xmind-sdk-python-master/dist/xmind-0.1a0-py3.7.egg
xxmind/file/xmind-sdk-python-master/dist/xmind-0.1a0.tar.gz
xxmind/file/xmind-sdk-python-master/xmind/__init__.py
xxmind/file/xmind-sdk-python-master/xmind/__init__.pyc
xxmind/file/xmind-sdk-python-master/xmind.egg-info/PKG-INFO
xxmind/file/xmind-sdk-python-master/xmind.egg-info/SOURCES.txt
xxmind/file/xmind-sdk-python-master/xmind.egg-info/dependency_links.txt
xxmind/file/xmind-sdk-python-master/xmind.egg-info/requires.txt
xxmind/file/xmind-sdk-python-master/xmind.egg-info/top_level.txt
