Metadata-Version: 2.1
Name: xxmind
Version: 0.5.2
Summary: xxmind是将xmind固定格式转为xlsx的转换工具。
Home-page: https://pypi.org/project/xxmind/#description
Author: goblinintree
Author-email: goblinintree@126.com
License: MIT
Keywords: xlsx,excel,xmind
Platform: all
Classifier: Environment :: Web Environment
Classifier: License :: OSI Approved :: MIT License
Classifier: Operating System :: Microsoft
Classifier: Programming Language :: Python :: 3.7
